aquastilla_softener/__init__.py
aquastilla_softener/aquastilla.py
aquastilla_softener-0.4.2.dist-info/licenses/LICENSE
aquastilla_softener-0.4.2.dist-info/METADATA
aquastilla_softener-0.4.2.dist-info/WHEEL
aquastilla_softener-0.4.2.dist-info/top_level.txt
aquastilla_softener-0.4.2.dist-info/RECORD
