Metadata-Version: 2.4
Name: aquastilla_softener
Version: 0.4.2
Summary: Library to fetch data from Aquastilla softener from Viessmann API
Home-page: https://github.com/alakdae/aquastilla-softener
Author: Tomasz Szymanowicz
Author-email: alakdae@gmail.com
License: GPL
Keywords: aquastilla softener aquastilla_softener
License-File: LICENSE
Dynamic: author
Dynamic: author-email
Dynamic: description
Dynamic: description-content-type
Dynamic: home-page
Dynamic: keywords
Dynamic: license
Dynamic: license-file
Dynamic: summary
